sentry_covdefaults_disable_branch_coverage.py
sentry_covdefaults_disable_branch_coverage-1.0.2.dist-info/LICENSE
sentry_covdefaults_disable_branch_coverage-1.0.2.dist-info/METADATA
sentry_covdefaults_disable_branch_coverage-1.0.2.dist-info/WHEEL
sentry_covdefaults_disable_branch_coverage-1.0.2.dist-info/top_level.txt
sentry_covdefaults_disable_branch_coverage-1.0.2.dist-info/RECORD
