Metadata-Version: 2.1
Name: sentry_covdefaults_disable_branch_coverage
Version: 1.0.2
Summary: disables `run:branch` for coverage (enabled by default with covdefaults)
Home-page: https://github.com/getsentry/sentry-covdefaults-disable-branch-coverage
Author: Sentry
Author-email: oss@sentry.io
License: Apache-2.0
Classifier: License :: OSI Approved :: Apache Software License
Classifier: Programming Language :: Python :: 3
Classifier: Programming Language :: Python :: 3 :: Only
Classifier: Programming Language :: Python :: Implementation :: CPython
Classifier: Programming Language :: Python :: Implementation :: PyPy
Requires-Python: >=3.9
License-File: LICENSE
Requires-Dist: coverage
